setup.py
pynzb/__init__.py
pynzb/base.py
pynzb/etree_nzb.py
pynzb/expat_nzb.py
pynzb/lxml_nzb.py
pynzb/tests.py
pynzb.egg-info/PKG-INFO
pynzb.egg-info/SOURCES.txt
pynzb.egg-info/dependency_links.txt
pynzb.egg-info/not-zip-safe
pynzb.egg-info/requires.txt
pynzb.egg-info/top_level.txt