Metadata-Version: 1.0
Name: pynzb
Version: 0.1.0
Summary: pynzb is a unified API for parsing NZB files, with several concrete implementations included
Home-page: http://github.com/ericflo/pynzb/tree/master
Author: Eric Florenzano
Author-email: floguy@gmail.com
License: BSD
Keywords: nzb,parser,xml
Platform: UNKNOWN
Classifier: Programming Language :: Python
Classifier: Topic :: Software Development :: Libraries :: Python Modules
